gpkg.object_detect-0.5.1-py2.7-nspkg.pth
gpkg/object_detect/__init__.py
gpkg/object_detect/_config.py
gpkg/object_detect/_patch.py
gpkg/object_detect/detect.py
gpkg/object_detect/eval.py
gpkg/object_detect/export_and_freeze.py
gpkg/object_detect/guild.yml
gpkg/object_detect/train.py
gpkg/object_detect/voc_images_prepare.py
gpkg/object_detect/config/extra/quantize.yml
gpkg/object_detect/config/models/faster-rcnn-resnet-101.yml
gpkg/object_detect/config/models/faster-rcnn-resnet-50.yml
gpkg/object_detect/config/models/ssd-mobilenet-v2.yml
gpkg/object_detect/config/train/rcnn-train-default.yml
gpkg/object_detect/config/train/rcnn-transfer-learn-default.yml
gpkg/object_detect/config/train/ssd-train-default.yml
gpkg/object_detect/config/train/ssd-transfer-learn-default.yml
gpkg.object_detect-0.5.1.dist-info/METADATA
gpkg.object_detect-0.5.1.dist-info/PACKAGE
gpkg.object_detect-0.5.1.dist-info/RECORD
gpkg.object_detect-0.5.1.dist-info/WHEEL
gpkg.object_detect-0.5.1.dist-info/namespace_packages.txt
gpkg.object_detect-0.5.1.dist-info/top_level.txt
