Metadata-Version: 2.1
Name: gpkg.object-detect
Version: 0.5.1
Summary: Object detection support (Guild AI)
Home-page: https://github.com/guildai/packages/tree/master/gpkg/object_detect
Author: Guild AI
Author-email: packages@guild.ai
License: Apache 2.0
Keywords: gpkg
Platform: UNKNOWN
Requires-Dist: gpkg.slim
Requires-Dist: Cython
Requires-Dist: contextlib2
Requires-Dist: lxml
Requires-Dist: matplotlib
Requires-Dist: pillow
Requires-Dist: pycocotools
